ceph_nvmeof-1.5.1.dist-info/METADATA
ceph_nvmeof-1.5.1.dist-info/WHEEL
ceph_nvmeof-1.5.1.dist-info/entry_points.txt
ceph_nvmeof-1.5.1.dist-info/licenses/LICENSE
control/__init__.py
control/__main__.py
control/cephutils.py
control/cli.py
control/cluster.py
control/config.py
control/discovery.py
control/grpc.py
control/prometheus.py
control/proto/__init__.py
control/proto/gateway.proto
control/proto/gateway_pb2.py
control/proto/gateway_pb2.pyi
control/proto/gateway_pb2_grpc.py
control/proto/monitor.proto
control/proto/monitor_pb2.py
control/proto/monitor_pb2.pyi
control/proto/monitor_pb2_grpc.py
control/rebalance.py
control/server.py
control/state.py
control/utils.py
ceph_nvmeof-1.5.1.dist-info/RECORD
