Metadata-Version: 2.1
Name: ceph-nvmeof
Version: 1.5.1
Summary: Service to provide Ceph storage over NVMe-oF protocol
Author-Email: Ilya Dryomov <idryomov@gmail.com>, Mykola Golub <mykola.golub@clyso.com>, Sandy Kaur <sandy.kaur@ibm.com>, Ernesto Puerta <epuertat@redhat.com>, Yin Congmin <congmin.yin@intel.com>, Scott Peterson <scott.d.peterson@intel.com>, Jason Dillaman <dillaman@redhat.com>, Anita Shekar <anita.shekar@ibm.com>
License: GNU LESSER GENERAL PUBLIC LICENSE
Project-URL: repository, https://github.com/ceph/ceph-nvmeof.git
Requires-Python: >3.9.1
Requires-Dist: grpcio~=1.53.0
Requires-Dist: grpcio_tools~=1.53.0
Requires-Dist: tabulate>=0.9.0
Requires-Dist: pyyaml>=6.0.1
Requires-Dist: prometheus_client~=0.19.0
Requires-Dist: netifaces~=0.11.0
Requires-Dist: cryptography>=43.0.3
